{
  "slug": "automatizacion-de-procesos",
  "title": "Automatización de Procesos & IA",
  "mode": "template",
  "accent_color": "#2f80ed",
  "seo": {
    "title": "Immoral Growth Group - Tu partner estratégico de crecimiento digital",
    "meta_description": null,
    "og_image": null
  },
  "hero": {
    "eyebrow": "Automatización de Procesos + IA:",
    "h1_html": "Eficiencia Inteligente<br>Diseñada a Medida",
    "subtitle": "Diseñamos automatizaciones e inteligencia artificial adaptadas a tus procesos para reducir fricción, ganar eficiencia y escalar con criterio."
  },
  "final_cta": {
    "title_html": "¿Listo para llevar tu empresa al siguiente nivel con <span class=\"text-[#2f80ed]\">automatización inteligente?</span>",
    "cta_text": "SOLICITA UNA AUDITORÍA GRATUITA",
    "cta_href": "contacto.html"
  }
}
